LICENSE.txt
MANIFEST.in
README.md
VERSION.txt
requirements.txt
setup.cfg
setup.py
Pabiana.egg-info/PKG-INFO
Pabiana.egg-info/SOURCES.txt
Pabiana.egg-info/dependency_links.txt
Pabiana.egg-info/not-zip-safe
Pabiana.egg-info/requires.txt
Pabiana.egg-info/top_level.txt
pabiana/__init__.py
pabiana/__main__.py
pabiana/abcs.py
pabiana/parsers.py
pabiana/templates.py
pabiana/utils.py
pabiana/zmqs/__init__.py
pabiana/zmqs/area.py
pabiana/zmqs/extensions.py
pabiana/zmqs/node.py
pabiana/zmqs/runner.py
pabiana/zmqs/utils.py