Metadata-Version: 2.1
Name: Pabiana
Version: 0.2.3
Summary: A minimalistic framework to build distributed cognitive applications based on ØMQ
Home-page: https://github.com/kankiri/pabiana
Author: Alexander Schöberl
Author-email: alexander.schoeberl@gmail.com
License: MIT
Keywords: framework,cognitive,distributed,ØMQ
Platform: UNKNOWN
